hako/__init__.py
hako/cli.py
hako/config.py
hako/get.py
hako/list.py
hako/login.py
hako/remove.py
hako/share.py
hako/upload.py
hako/utils/__init__.py
hako/utils/filesize.py
hako-0.0.5.dist-info/LICENSE
hako-0.0.5.dist-info/METADATA
hako-0.0.5.dist-info/WHEEL
hako-0.0.5.dist-info/entry_points.txt
hako-0.0.5.dist-info/top_level.txt
hako-0.0.5.dist-info/RECORD
