Metadata-Version: 2.1
Name: hako
Version: 0.0.5
Summary: CLI for Hako command line cloud file storage.
Home-page: https://hako.ai/
Author: David Chan
License: MIT
Project-URL: Documentation, https://hako.ai/docs
Keywords: cloud,filesystem,manager,cli,command line
Platform: any
Classifier: Development Status :: 2 - Pre-Alpha
Classifier: Programming Language :: Python
Classifier: Programming Language :: Python :: 3
Classifier: Programming Language :: Python :: 3 :: Only
Classifier: Environment :: Console
Classifier: License :: OSI Approved :: MIT License
Classifier: Operating System :: OS Independent
Classifier: Topic :: System :: Filesystems
Classifier: Topic :: Utilities
Classifier: Intended Audience :: Developers
Classifier: Intended Audience :: System Administrators
Classifier: Intended Audience :: Information Technology
Classifier: Intended Audience :: Science/Research
License-File: LICENSE
Requires-Dist: click (>=8.1.2)
Requires-Dist: rich (>=12.2.0)
Requires-Dist: requests (>=2.22.0)
Requires-Dist: cryptography (>=36.0.2)
Requires-Dist: pick (>=1.2.0)
Requires-Dist: requests-toolbelt (>=0.9.1)
Requires-Dist: bcrypt (>=3.2.0)
